py3db/Connection.py
py3db/Db.py
py3db/__init__.py
py3db/connector/__init__.py
py3db/connector/mysql.py
py3db/elasticsearch/__init__.py
py3db/elasticsearch/elastic_search.py
py3db/log/Log.py
py3db/log/__init__.py
py3db/mongodb/__init__.py
py3db/mongodb/mongodb.py
py3db/mysql/__init__.py
py3db/mysql/mysql.py
py3db/sqlite/__init__.py
py3db/sqlite/sqlite.py
py3db-0.0.19.dist-info/LICENSE.txt
py3db-0.0.19.dist-info/METADATA
py3db-0.0.19.dist-info/WHEEL
py3db-0.0.19.dist-info/top_level.txt
py3db-0.0.19.dist-info/RECORD
