Metadata-Version: 2.1
Name: py3db
Version: 0.0.19
Summary: connect to database
Home-page: https://gitee.com/gan_jian_wen_main
Author: 甘建文
Author-email: 1727949032@qq.com
License: UNKNOWN
Platform: UNKNOWN
Classifier: Programming Language :: Python :: 3
Classifier: License :: OSI Approved :: MIT License
Classifier: Operating System :: OS Independent
Requires-Python: >=3.6
Requires-Dist: pymongo
Requires-Dist: pymysql
